caaalle/__init__.py
caaalle/math.py
caaalle-3.0.0.dist-info/LICENSE
caaalle-3.0.0.dist-info/METADATA
caaalle-3.0.0.dist-info/WHEEL
caaalle-3.0.0.dist-info/top_level.txt
caaalle-3.0.0.dist-info/RECORD
