Metadata-Version: 2.1
Name: caaalle
Version: 3.0.0
Summary: caaalle
Home-page: https://github.com/caalle/caaalle
Author: Carl Larsson
Author-email: example@gmail.com
License: Apache 2.0
Keywords: caaalle
Platform: UNKNOWN
Classifier: Intended Audience :: Developers
Classifier: Programming Language :: Python :: 3.8
Classifier: Programming Language :: Python :: 3.7
Classifier: Programming Language :: Python :: 3.6
Classifier: Programming Language :: Python :: 3.5
Requires-Python: >=3.5.*
